axios/__init__.py
axios/__main__.py
axios/cli.py
axios/models.py
axios/navigator.py
axios/result.py
axios-0.4.0.dist-info/METADATA
axios-0.4.0.dist-info/WHEEL
axios-0.4.0.dist-info/entry_points.txt
axios-0.4.0.dist-info/top_level.txt
axios-0.4.0.dist-info/RECORD
