Metadata-Version: 2.1
Name: axios
Version: 0.4.0
Summary: Command line utility to access https://family.axioscloud.it
Home-page: https://github.com/zmoog/axios
Author: Maurizio Branca
License: Apache License, Version 2.0
Project-URL: Issues, https://github.com/zmoog/axios/issues
Project-URL: CI, https://github.com/zmoog/axios/actions
Project-URL: Changelog, https://github.com/zmoog/axios/releases
Requires-Python: >=3.8
Provides-Extra: test
